{
    "Actors": {},
    "Item": {
        "types": ["Weapon", "Passive", "Talent", "Ability"],
        "templates": {
            "base": {
                "description": ""
            }
        },
        "Weapon": {
            "templates": ["base"],
            "damage": 0,
            "range": 0
        },
        "Passive": {
            "templates": ["base"]
        },
        "Talent": {
            "templates": ["base"],
            "bonus": 0
        },
        "Ability": {
            "templates": ["base"],
            "cost": 0
        }
    }
}